controls/__init__.py
controls/admin.py
controls/apps.py
controls/gql_mutations.py
controls/gql_queries.py
controls/models.py
controls/schema.py
controls/urls.py
controls/views.py
controls/migrations/0001_initial.py
controls/migrations/0002_mobileenrollmentmutation.py
controls/migrations/__init__.py
controls/tests/__init__.py
controls/tests/conftest.py
controls/tests/test_gql.py
controls/tests/test_models.py
controls/tests/test_settings.py
openimis_be_controls-1.2.0.dist-info/LICENSE.md
openimis_be_controls-1.2.0.dist-info/METADATA
openimis_be_controls-1.2.0.dist-info/WHEEL
openimis_be_controls-1.2.0.dist-info/top_level.txt
openimis_be_controls-1.2.0.dist-info/RECORD
