Metadata-Version: 2.1
Name: openimis-be-controls
Version: 1.2.0
Summary: The openIMIS Backend controls reference module.
Home-page: https://openimis.org/
Author: Christophe Philemotte
Author-email: cphilemotte@bluesquarehub.com
License: GNU AGPL v3
Classifier: Environment :: Web Environment
Classifier: Framework :: Django
Classifier: Framework :: Django :: 3.0
Classifier: Intended Audience :: Developers
Classifier: License :: OSI Approved :: GNU Affero General Public License v3
Classifier: Operating System :: OS Independent
Classifier: Programming Language :: Python
Classifier: Programming Language :: Python :: 3.8
License-File: LICENSE.md
Requires-Dist: django
Requires-Dist: djangorestframework
Requires-Dist: django-filter~=22.1
Requires-Dist: openimis-be-core
Requires-Dist: graphene-django
Provides-Extra: dev
Requires-Dist: pytest; extra == "dev"
Requires-Dist: pytest-django; extra == "dev"
